<?xml version="1.0" encoding="UTF-8"?>
<!DOCTYPE filesystem PUBLIC "-//NetBeans//DTD Filesystem 1.2//EN" "http://www.netbeans.org/dtds/filesystem-1_2.dtd">
<filesystem>
    <folder name="Actions">
        <folder name="Window">
            <file name="de-unibielefeld-gi-kotte-laborprogramm-plateViewer-PlateViewerTopComponentAction.instance">
                <attr name="component" methodvalue="de.unibielefeld.gi.kotte.laborprogramm.plateViewer.PlateViewerTopComponent.findInstance"/>
                <attr name="displayName" bundlevalue="de.unibielefeld.gi.kotte.laborprogramm.plateViewer.Bundle#CTL_PlateViewerTopComponentAction"/>
                <attr name="instanceCreate" methodvalue="org.openide.windows.TopComponent.openAction"/>
            </file>
        </folder>
    </folder>
    <folder name="Menu">
        <folder name="Window">
            <file name="PlateViewerTopComponentAction.shadow">
                <attr name="originalFile" stringvalue="Actions/Window/de-unibielefeld-gi-kotte-laborprogramm-plateViewer-PlateViewerTopComponentAction.instance"/>
            </file>
        </folder>
    </folder>
    <folder name="Windows2">
        <folder name="Components">
            <file name="PlateViewerTopComponentTopComponent.settings" url="PlateViewerTopComponentTopComponentSettings.xml"/>
        </folder>
        <folder name="Modes">
            <folder name="editor">
                <file name="PlateViewerTopComponentTopComponent.wstcref" url="PlateViewerTopComponentTopComponentWstcref.xml"/>
            </folder>
        </folder>
    </folder>
</filesystem>
